{
  "defaultSeverity": "warning",
  "extends": [
    "tslint:recommended",
    "tslint-react",
    "tslint-microsoft-contrib",
    "tslint-consistent-codestyle",
    "tslint-plugin-prettier",
    "tslint-config-prettier"
  ],
  "linterOptions": {
    "exclude": [
      "config/**/*.js",
      "node_modules/**/*.ts",
      "coverage/lcov-report/*.js"
    ]
  },
  "rules": {
    "no-unused-variable": false,
    "no-unused-expression": false,
    "no-submodule-imports": false,
    "no-implicit-dependencies": [true, ["src"]],
    "export-name": false,
    "max-line-length": [true, 120],
    "no-import-side-effect": [true, { "ignore-module": "(\\.html|\\.css)$" }],
    "no-relative-imports": ["allow-siblings"],
    "prettier": true,
    "no-default-export": true,
    "no-unsafe-any": false,
    "no-any": false
  }
}
